auth0_mgr/__init__.py
auth0_mgr/tokens.py
auth0_mgr/misc/__init__.py
auth0_mgr/misc/keycloak.py
auth0_mgr/models/__init__.py
auth0_mgr/models/user.py
auth0_mgr/scripts/__init__.py
auth0_mgr/scripts/get_logs.py
auth0_mgr/scripts/import_users_from_keycloak_db.py
auth0_mgr/scripts/update_users_from_json.py
auth0_mgr/users/__init__.py
auth0_mgr/users/user_manager.py
presalytics_auth0_management_extensions-0.1.4.dist-info/METADATA
presalytics_auth0_management_extensions-0.1.4.dist-info/WHEEL
presalytics_auth0_management_extensions-0.1.4.dist-info/top_level.txt
presalytics_auth0_management_extensions-0.1.4.dist-info/RECORD
