Metadata-Version: 2.1
Name: presalytics-auth0-management-extensions
Version: 0.1.4
Summary: Presalytics Auth0 Management Extensions
Home-page: https://presalytics.io/docs
Author-email: inquiries@presalytics.io
License: UNKNOWN
Keywords: Presalytics,Auth0
Platform: UNKNOWN
Requires-Dist: auth0-python (>=3.9.2)
Requires-Dist: environs (>=7.4.0)
